setup.py
empath/__init__.py
empath/core.py
empath/helpers.py
empath.egg-info/PKG-INFO
empath.egg-info/SOURCES.txt
empath.egg-info/dependency_links.txt
empath.egg-info/requires.txt
empath.egg-info/top_level.txt
empath/data/categories.tsv
empath/data/user/blank
test/test.py