Metadata-Version: 1.1
Name: empath
Version: 0.88
Summary: A tool for text analysis
Home-page: https://github.com/Ejhfast/empath-client
Author: Ethan Fast
Author-email: ejhfast@gmail.com
License: UNKNOWN
Download-URL: https://github.com/Ejhfast/meta/empath-client/0.39
Keywords: social science,lexicon,text analysis
Platform: UNKNOWN
